sof_utils/__init__.py
sof_utils/dataset_utils.py
sof_utils/dicom.py
sof_utils/export.py
sof_utils/misc.py
sof_utils/tf_record_creation_util.py
sof_utils-0.2.0.data/scripts/sof-convert-labels
sof_utils-0.2.0.data/scripts/sof-convert-tfds
sof_utils-0.2.0.data/scripts/sof-detect-keypoints
sof_utils-0.2.0.data/scripts/sof-dicom-corrupted
sof_utils-0.2.0.data/scripts/sof-dicom-meta
sof_utils-0.2.0.data/scripts/sof-export-images
sof_utils-0.2.0.data/scripts/sof-keypoint-outliers
sof_utils-0.2.0.dist-info/LICENSE
sof_utils-0.2.0.dist-info/METADATA
sof_utils-0.2.0.dist-info/WHEEL
sof_utils-0.2.0.dist-info/top_level.txt
sof_utils-0.2.0.dist-info/RECORD
