Metadata-Version: 2.1
Name: sof-utils
Version: 0.2.0
Summary: Small utilities to aid working with the SOF dataset
Home-page: https://github.com/ithron/SOF-Utils
Author: Stefan Reinhold
Author-email: stefan@sreinhold.com
License: UNKNOWN
Platform: UNKNOWN
Classifier: Environment :: Console
Classifier: Intended Audience :: Science/Research
Classifier: Programming Language :: Python :: 3
Classifier: License :: OSI Approved :: BSD License
Classifier: Operating System :: OS Independent
Requires-Python: >=3.6
License-File: LICENSE
Requires-Dist: pydicom
Requires-Dist: pathlib
Requires-Dist: tqdm
Requires-Dist: tensorflow-datasets
Requires-Dist: numpy
Requires-Dist: scipy
